{
    "Ar36": {
        "error": 0.00033196416050150165,
        "error_type": "SEM",
        "filter_outliers_dict": {
            "filter_outliers": true,
            "iterations": 1,
            "std_devs": 3,
            "use_iqr_filtering": false,
            "use_standard_deviation_filtering": false
        },
        "fit": "Linear",
        "fn": 92,
        "include_baseline_error": true,
        "n": 92,
        "outlier_excluded": [],
        "reviewed": true,
        "user_excluded": [],
        "value": 0.007113577687227905
    },
    "Ar37": {
        "error": 0.007307736668421322,
        "error_type": "SEM",
        "filter_outliers_dict": {
            "filter_outliers": true,
            "iterations": 1,
            "std_devs": 3,
            "use_iqr_filtering": false,
            "use_standard_deviation_filtering": false
        },
        "fit": "Linear",
        "fn": 90,
        "include_baseline_error": true,
        "n": 92,
        "outlier_excluded": [
            8,
            57
        ],
        "reviewed": true,
        "user_excluded": [],
        "value": 0.043807064814240106
    },
    "Ar38": {
        "error": 0.008695826604314416,
        "error_type": "SEM",
        "filter_outliers_dict": {
            "filter_outliers": true,
            "iterations": 1,
            "std_devs": 3,
            "use_iqr_filtering": false,
            "use_standard_deviation_filtering": false
        },
        "fit": "Linear",
        "fn": 91,
        "include_baseline_error": true,
        "n": 92,
        "outlier_excluded": [
            0
        ],
        "reviewed": true,
        "user_excluded": [],
        "value": 0.11285437933428508
    },
    "Ar39": {
        "error": 0.016750022147767486,
        "error_type": "SEM",
        "filter_outliers_dict": {
            "filter_outliers": true,
            "iterations": 1,
            "std_devs": 3,
            "use_iqr_filtering": false,
            "use_standard_deviation_filtering": false
        },
        "fit": "Linear",
        "fn": 92,
        "include_baseline_error": true,
        "n": 92,
        "outlier_excluded": [],
        "reviewed": true,
        "user_excluded": [],
        "value": 8.192957559977605
    },
    "Ar40": {
        "error": 0.02309416027073801,
        "error_type": "SEM",
        "filter_outliers_dict": {
            "filter_outliers": true,
            "iterations": 1,
            "std_devs": 3,
            "use_iqr_filtering": false,
            "use_standard_deviation_filtering": false
        },
        "fit": "Linear",
        "fn": 92,
        "include_baseline_error": true,
        "n": 92,
        "outlier_excluded": [],
        "reviewed": true,
        "user_excluded": [],
        "value": 68.74134239302099
    },
    "Ar41": {
        "error": 0.007051498210189893,
        "error_type": "SEM",
        "filter_outliers_dict": {
            "filter_outliers": true,
            "iterations": 1,
            "std_devs": 2
        },
        "fit": "linear",
        "value": 0.09500955823756788
    }
}